revenium_middleware_anthropic/__init__.py
revenium_middleware_anthropic/bedrock_adapter.py
revenium_middleware_anthropic/middleware.py
revenium_middleware_anthropic/provider.py
revenium_middleware_anthropic/trace_fields.py
revenium_middleware_anthropic-0.4.0.dist-info/licenses/LICENSE
revenium_middleware_anthropic-0.4.0.dist-info/METADATA
revenium_middleware_anthropic-0.4.0.dist-info/WHEEL
revenium_middleware_anthropic-0.4.0.dist-info/top_level.txt
revenium_middleware_anthropic-0.4.0.dist-info/RECORD
